{"GlobalPropertiesHash":"2ilJ2M8+ZdH0swl4cXFj9Ji8kay0R08ISE/fEc+OL0o=","FingerprintPatternsHash":"8ZRc1sGeVrPBx4lD717BgRaQekyh78QKV9SKsdt638U=","PropertyOverridesHash":"8ZRc1sGeVrPBx4lD717BgRaQekyh78QKV9SKsdt638U=","InputHashes":["l76XJ3as3qC9tX4Wj5xC2LBr0YXVs6gNmfsuJ\u002BUHL/s=","n41thz5Y53uBcJ0X8MKUtXlodKsHxv5jqyad9RO8iF8=","ezuKzfN5lnSedAk/EZ0G5ohkWmwdVJp0qlZ6rE3IZF4=","PZvzFq2G6ZOoEkOfCH1yHlg0ja3DtXd6TG3PSv42kU4="],"CachedAssets":{"n41thz5Y53uBcJ0X8MKUtXlodKsHxv5jqyad9RO8iF8=":{"Identity":"C:\\Projects\\MehmetEminProje\\UI\\obj\\Debug\\net10.0\\compressed\\y77cf4enue-{0}-ijpqwr52dg-ijpqwr52dg.gz","SourceId":"UI","SourceType":"Discovered","ContentRoot":"C:\\Projects\\MehmetEminProje\\UI\\obj\\Debug\\net10.0\\compressed\\","BasePath":"/","RelativePath":"css/site#[.{fingerprint=ijpqwr52dg}]?.css.gz","AssetKind":"All","AssetMode":"All","AssetRole":"Alternative","AssetMergeBehavior":null,"AssetMergeSource":"","RelatedAsset":"C:\\Projects\\MehmetEminProje\\UI\\wwwroot\\css\\site.css","AssetTraitName":"Content-Encoding","AssetTraitValue":"gzip","Fingerprint":"qdwm5xheiz","Integrity":"biYVFc4PJ4hM3TXgWHroA/6FyaYmZIK9O6lrmLEBWkc=","CopyToOutputDirectory":"Never","CopyToPublishDirectory":"PreserveNewest","OriginalItemSpec":"C:\\Projects\\MehmetEminProje\\UI\\wwwroot\\css\\site.css","FileLength":957,"LastWriteTime":"2026-05-17T14:49:48.6475068+00:00"},"PZvzFq2G6ZOoEkOfCH1yHlg0ja3DtXd6TG3PSv42kU4=":{"Identity":"C:\\Projects\\MehmetEminProje\\UI\\obj\\Debug\\net10.0\\compressed\\k83gvgtd2a-{0}-zp5uhyghf0-zp5uhyghf0.gz","SourceId":"UI","SourceType":"Discovered","ContentRoot":"C:\\Projects\\MehmetEminProje\\UI\\obj\\Debug\\net10.0\\compressed\\","BasePath":"/","RelativePath":"js/site#[.{fingerprint=zp5uhyghf0}]?.js.gz","AssetKind":"All","AssetMode":"All","AssetRole":"Alternative","AssetMergeBehavior":null,"AssetMergeSource":"","RelatedAsset":"C:\\Projects\\MehmetEminProje\\UI\\wwwroot\\js\\site.js","AssetTraitName":"Content-Encoding","AssetTraitValue":"gzip","Fingerprint":"ath18smqnv","Integrity":"buj4HJlrbc9PKc8r49JoM4a\u002BGpTa9\u002BfZt70Iv7\u002B/7\u002Bs=","CopyToOutputDirectory":"Never","CopyToPublishDirectory":"PreserveNewest","OriginalItemSpec":"C:\\Projects\\MehmetEminProje\\UI\\wwwroot\\js\\site.js","FileLength":3131,"LastWriteTime":"2026-05-23T12:58:51.762154+00:00"},"l76XJ3as3qC9tX4Wj5xC2LBr0YXVs6gNmfsuJ\u002BUHL/s=":{"Identity":"C:\\Projects\\MehmetEminProje\\UI\\obj\\Debug\\net10.0\\compressed\\r5d9vsxkhx-{0}-h2wbpcybff-h2wbpcybff.gz","SourceId":"UI","SourceType":"Discovered","ContentRoot":"C:\\Projects\\MehmetEminProje\\UI\\obj\\Debug\\net10.0\\compressed\\","BasePath":"/","RelativePath":"css/block-editor#[.{fingerprint=h2wbpcybff}]?.css.gz","AssetKind":"All","AssetMode":"All","AssetRole":"Alternative","AssetMergeBehavior":null,"AssetMergeSource":"","RelatedAsset":"C:\\Projects\\MehmetEminProje\\UI\\wwwroot\\css\\block-editor.css","AssetTraitName":"Content-Encoding","AssetTraitValue":"gzip","Fingerprint":"ycue5zgd3q","Integrity":"zp2rgZZaJDnkS\u002BjQLi8rJtyEuIMzHTwwuGnsJelsqdg=","CopyToOutputDirectory":"Never","CopyToPublishDirectory":"PreserveNewest","OriginalItemSpec":"C:\\Projects\\MehmetEminProje\\UI\\wwwroot\\css\\block-editor.css","FileLength":912,"LastWriteTime":"2026-05-23T11:31:37.7077275+00:00"},"ezuKzfN5lnSedAk/EZ0G5ohkWmwdVJp0qlZ6rE3IZF4=":{"Identity":"C:\\Projects\\MehmetEminProje\\UI\\obj\\Debug\\net10.0\\compressed\\r6mzsqia01-{0}-zi4v9m5rc5-zi4v9m5rc5.gz","SourceId":"UI","SourceType":"Discovered","ContentRoot":"C:\\Projects\\MehmetEminProje\\UI\\obj\\Debug\\net10.0\\compressed\\","BasePath":"/","RelativePath":"js/block-editor#[.{fingerprint=zi4v9m5rc5}]?.js.gz","AssetKind":"All","AssetMode":"All","AssetRole":"Alternative","AssetMergeBehavior":null,"AssetMergeSource":"","RelatedAsset":"C:\\Projects\\MehmetEminProje\\UI\\wwwroot\\js\\block-editor.js","AssetTraitName":"Content-Encoding","AssetTraitValue":"gzip","Fingerprint":"bf0rj7fw8u","Integrity":"55l\u002BlirE2mApKrUyDqM26y2\u002B3mizAYXsx9Eta9kywMQ=","CopyToOutputDirectory":"Never","CopyToPublishDirectory":"PreserveNewest","OriginalItemSpec":"C:\\Projects\\MehmetEminProje\\UI\\wwwroot\\js\\block-editor.js","FileLength":2927,"LastWriteTime":"2026-05-23T12:58:51.762154+00:00"}},"CachedCopyCandidates":{}}